MANIFEST.in
README.md
setup.py
gor4/__init__.py
gor4/gor4.py
gor4.egg-info/PKG-INFO
gor4.egg-info/SOURCES.txt
gor4.egg-info/dependency_links.txt
gor4.egg-info/pbr.json
gor4.egg-info/requires.txt
gor4.egg-info/top_level.txt
gor4/data/New_KS.267.obs
gor4/data/New_KS.267.seq
gor4/data/README.md
gor4/data/new-gor4.obs
gor4/data/new-gor4.seq
src/api.c
src/build.py
src/defines.h
src/gor4-base.c
src/gor4-base.h
src/nrutil.c
src/nrutil.h
test/test_gor4.py